app/__init__.py
app/wCLAMs.py
app/static/bootstrap.css
app/static/bootstrap.js
app/static/jquery-3.3.1.min.js
app/static/jquery.blockUI.js
app/static/jquery.form.min.js
app/static/sample.csv
app/templates/home.html
wCLAMs/__init__.py
wCLAMs/run.py
wCLAMs/wCLAMs.py
wCLAMs/static/bootstrap.css
wCLAMs/static/bootstrap.js
wCLAMs/static/jquery-3.3.1.min.js
wCLAMs/static/jquery.blockUI.js
wCLAMs/static/jquery.form.min.js
wCLAMs/static/sample.csv
wCLAMs/templates/home.html
wCLAMs-0.1.3.dist-info/LICENCE
wCLAMs-0.1.3.dist-info/METADATA
wCLAMs-0.1.3.dist-info/WHEEL
wCLAMs-0.1.3.dist-info/top_level.txt
wCLAMs-0.1.3.dist-info/RECORD
